{
  "objectInfo" : {
    "id" : "7FHed6hfWlThp3RfKeTWci",
    "name" : "tf_sfdc_reverse_pull_myr",
    "type" : "WORKFLOW",
    "metadata" : {
      "modelVersion" : {
        "major" : 0,
        "minor" : 0
      },
      "repoInfo" : {
        "repoHandle" : "0102UZ0N00000000002S"
      },
      "contextAttributes" : [ {
        "name" : "id",
        "value" : "@1"
      } ],
      "additionalInfo" : {
        "description" : null,
        "contentType" : "JSON",
        "documentState" : "VALID"
      }
    }
  },
  "dataFileExtension" : "zip",
  "updateTime" : "2023-08-24T02:43:10.526Z",
  "objectRefs" : [ {
    "id" : "imh1Dm31LMpfLqZiDl5MSa",
    "name" : "mt_rp_sf_user",
    "type" : "MTT",
    "metadata" : {
      "modelVersion" : {
        "major" : 0,
        "minor" : 0
      },
      "repoInfo" : {
        "repoHandle" : "0102UZ0Z0000000000Y4"
      },
      "contextAttributes" : [ {
        "name" : "id",
        "value" : "@1"
      } ],
      "additionalInfo" : {
        "description" : "",
        "contentType" : "JSON",
        "documentState" : "VALID"
      }
    },
    "path" : "/Explore/MYR_Migration_SFDC/Reversepull_objects"
  }, {
    "id" : "39DvPyl4wrTbC64pKY0PW9",
    "name" : "mt_rp_sf_billing_account",
    "type" : "MTT",
    "metadata" : {
      "modelVersion" : {
        "major" : 0,
        "minor" : 0
      },
      "repoInfo" : {
        "repoHandle" : "0102UZ0Z0000000000XH"
      },
      "contextAttributes" : [ {
        "name" : "id",
        "value" : "@1"
      } ],
      "additionalInfo" : {
        "description" : "",
        "contentType" : "JSON",
        "documentState" : "VALID"
      }
    },
    "path" : "/Explore/MYR_Migration_SFDC/Reversepull_objects"
  }, {
    "id" : "6vsFzobozOVkKW6ZYz8dss",
    "name" : "mt_m_rp_sf_customer_account",
    "type" : "MTT",
    "metadata" : {
      "modelVersion" : {
        "major" : 0,
        "minor" : 0
      },
      "repoInfo" : {
        "repoHandle" : "0102UZ0Z0000000000Y0"
      },
      "contextAttributes" : [ {
        "name" : "id",
        "value" : "@1"
      } ],
      "additionalInfo" : {
        "description" : "",
        "contentType" : "JSON",
        "documentState" : "VALID"
      }
    },
    "path" : "/Explore/MYR_Migration_SFDC/Reversepull_objects"
  }, {
    "id" : "8Pt1Us7C109fXjJMuhqk8S",
    "name" : "mt_rp_sf_recordtype",
    "type" : "MTT",
    "metadata" : {
      "modelVersion" : {
        "major" : 0,
        "minor" : 0
      },
      "repoInfo" : {
        "repoHandle" : "0102UZ0Z0000000000WR"
      },
      "contextAttributes" : [ {
        "name" : "id",
        "value" : "@1"
      } ],
      "additionalInfo" : {
        "description" : "",
        "contentType" : "JSON",
        "documentState" : "VALID"
      }
    },
    "path" : "/Explore/MYR_Migration_SFDC/Reversepull_objects"
  }, {
    "id" : "0mtqhVl6qJ8ltEm5P7Q1GP",
    "name" : "mt_rp_sf_address",
    "type" : "MTT",
    "metadata" : {
      "modelVersion" : {
        "major" : 0,
        "minor" : 0
      },
      "repoInfo" : {
        "repoHandle" : "0102UZ0Z0000000000W3"
      },
      "contextAttributes" : [ {
        "name" : "id",
        "value" : "@1"
      } ],
      "additionalInfo" : {
        "description" : "",
        "contentType" : "JSON",
        "documentState" : "VALID"
      }
    },
    "path" : "/Explore/MYR_Migration_SFDC/Reversepull_objects"
  }, {
    "id" : "1GcOixsWPnxgVtCfwcehIg",
    "name" : "mt_rp_sf_contact",
    "type" : "MTT",
    "metadata" : {
      "modelVersion" : {
        "major" : 0,
        "minor" : 0
      },
      "repoInfo" : {
        "repoHandle" : "0102UZ0Z0000000000XR"
      },
      "contextAttributes" : [ {
        "name" : "id",
        "value" : "@1"
      } ],
      "additionalInfo" : {
        "description" : "",
        "contentType" : "JSON",
        "documentState" : "VALID"
      }
    },
    "path" : "/Explore/MYR_Migration_SFDC/Reversepull_objects"
  } ]
}